shock_wave_compression/BackwardPropagationFromWindow.py
shock_wave_compression/ShockWaveExperiment.py
shock_wave_compression/__init__.py
shock_wave_compression/material_database/Kapton.py
shock_wave_compression/material_database/MgO.py
shock_wave_compression/material_database/Quartz.py
shock_wave_compression/material_database/__init__.py
shock_wave_compression/material_database/baseclass/Material.py
shock_wave_compression/material_database/baseclass/__init__.py
shock_wave_compression/material_states/Hugoniot.py
shock_wave_compression/material_states/Intersection.py
shock_wave_compression/material_states/Isentrope.py
shock_wave_compression/material_states/__init__.py
shock_wave_compression/material_states/isentrope_calculators/IntegratedIsentrope.py
shock_wave_compression/material_states/isentrope_calculators/ReflectedHugoniot.py
shock_wave_compression/material_states/isentrope_calculators/__init__.py
MSEE_MgO_UQ-0.1.16.dist-info/METADATA
MSEE_MgO_UQ-0.1.16.dist-info/WHEEL
MSEE_MgO_UQ-0.1.16.dist-info/top_level.txt
MSEE_MgO_UQ-0.1.16.dist-info/RECORD
